lisc/__init__.py
lisc/version.py
lisc/analysis/__init__.py
lisc/analysis/counts.py
lisc/analysis/time.py
lisc/analysis/words.py
lisc/collect/__init__.py
lisc/collect/citations.py
lisc/collect/counts.py
lisc/collect/info.py
lisc/collect/process.py
lisc/collect/terms.py
lisc/collect/time.py
lisc/collect/words.py
lisc/data/__init__.py
lisc/data/articles.py
lisc/data/articles_all.py
lisc/data/base_articles.py
lisc/data/meta_data.py
lisc/data/process.py
lisc/data/stopwords.py
lisc/data/term.py
lisc/data/utils.py
lisc/io/__init__.py
lisc/io/db.py
lisc/io/io.py
lisc/io/utils.py
lisc/modutils/__init__.py
lisc/modutils/decorators.py
lisc/modutils/dependencies.py
lisc/modutils/errors.py
lisc/objects/__init__.py
lisc/objects/base.py
lisc/objects/counts.py
lisc/objects/utils.py
lisc/objects/words.py
lisc/plts/__init__.py
lisc/plts/counts.py
lisc/plts/time.py
lisc/plts/utils.py
lisc/plts/wordcloud.py
lisc/plts/words.py
lisc/requester/__init__.py
lisc/requester/requester.py
lisc/tests/__init__.py
lisc/tests/conftest.py
lisc/tests/tdata.py
lisc/tests/tobjs.py
lisc/tests/tsettings.py
lisc/tests/tutils.py
lisc/tests/analysis/__init__.py
lisc/tests/analysis/test_counts.py
lisc/tests/analysis/test_time.py
lisc/tests/analysis/test_words.py
lisc/tests/collect/__init__.py
lisc/tests/collect/test_citations.py
lisc/tests/collect/test_counts.py
lisc/tests/collect/test_info.py
lisc/tests/collect/test_process.py
lisc/tests/collect/test_terms.py
lisc/tests/collect/test_time.py
lisc/tests/collect/test_words.py
lisc/tests/data/__init__.py
lisc/tests/data/test_articles.py
lisc/tests/data/test_articles_all.py
lisc/tests/data/test_base_articles.py
lisc/tests/data/test_meta_data.py
lisc/tests/data/test_process.py
lisc/tests/data/test_term.py
lisc/tests/data/test_utils.py
lisc/tests/io/__init__.py
lisc/tests/io/test_db.py
lisc/tests/io/test_io.py
lisc/tests/io/test_utils.py
lisc/tests/modutils/__init__.py
lisc/tests/modutils/test_decorators.py
lisc/tests/modutils/test_dependencies.py
lisc-0.4.0.dist-info/LICENSE
lisc-0.4.0.dist-info/METADATA
lisc-0.4.0.dist-info/WHEEL
lisc-0.4.0.dist-info/top_level.txt
lisc-0.4.0.dist-info/RECORD
