Metadata-Version: 2.1
Name: lisc
Version: 0.4.0
Summary: Literature Scanner
Home-page: https://github.com/lisc-tools/lisc
Download-URL: https://github.com/lisc-tools/lisc/releases
Author: Thomas Donoghue
Author-email: tdonoghue.research@gmail.com
Maintainer: Thomas Donoghue
Maintainer-email: tdonoghue.research@gmail.com
License: Apache License, 2.0
Project-URL: Documentation, https://lisc-tools.github.io/
Project-URL: Bug Reports, https://github.com/lisc-tools/lisc/issues
Project-URL: Source, https://github.com/lisc-tools/lisc
Keywords: web-scraping,meta-analysis,text-mining,scientific-publications,literature-mining,literature-review
Platform: any
Classifier: Development Status :: 5 - Production/Stable
Classifier: Intended Audience :: Science/Research
Classifier: Topic :: Scientific/Engineering
Classifier: License :: OSI Approved :: Apache Software License
Classifier: Operating System :: Microsoft :: Windows
Classifier: Operating System :: MacOS
Classifier: Operating System :: POSIX
Classifier: Operating System :: Unix
Classifier: Programming Language :: Python
Classifier: Programming Language :: Python :: 3.7
Classifier: Programming Language :: Python :: 3.8
Classifier: Programming Language :: Python :: 3.9
Classifier: Programming Language :: Python :: 3.10
Classifier: Programming Language :: Python :: 3.11
Classifier: Programming Language :: Python :: 3.12
Classifier: Programming Language :: Python :: 3.13
Requires-Python: >=3.7
License-File: LICENSE
Requires-Dist: numpy>=1.17.1
Requires-Dist: requests
Requires-Dist: lxml
Requires-Dist: beautifulsoup4
Provides-Extra: plot
Requires-Dist: matplotlib; extra == "plot"
Requires-Dist: seaborn; extra == "plot"
Requires-Dist: wordcloud; extra == "plot"
Provides-Extra: analysis
Requires-Dist: scipy; extra == "analysis"
Provides-Extra: all
Requires-Dist: matplotlib; extra == "all"
Requires-Dist: seaborn; extra == "all"
Requires-Dist: wordcloud; extra == "all"
Requires-Dist: scipy; extra == "all"
